{"version":1,"resource":"file:///home/naman/Desktop/Project/React%20Native/cpay/app/App.tsx","entries":[{"id":"NhmX.tsx","timestamp":1683367577583},{"id":"Tetz.tsx","timestamp":1683367615314},{"id":"ugZh.tsx","timestamp":1683367779619},{"id":"W1na.tsx","timestamp":1683367804097},{"id":"Yfk2.tsx","timestamp":1683368034002},{"id":"azEX.tsx","timestamp":1683368058867},{"id":"9Vqm.tsx","timestamp":1683369023441},{"id":"1jlX.tsx","timestamp":1683369040105},{"id":"arTF.tsx","timestamp":1683369074632},{"id":"lqsk.tsx","timestamp":1683369108155},{"id":"Z6it.tsx","timestamp":1683369118267},{"id":"bflM.tsx","timestamp":1683369164638},{"id":"DO5j.tsx","timestamp":1683369204656},{"id":"sI4S.tsx","timestamp":1683369254675},{"id":"hAK2.tsx","timestamp":1683369299633},{"id":"Yu9n.tsx","timestamp":1683371287446},{"id":"f8KT.tsx","timestamp":1683371322043},{"id":"ss3O.tsx","timestamp":1683371506226},{"id":"N2UG.tsx","timestamp":1683371539030},{"id":"dyAN.tsx","timestamp":1683371567755},{"id":"DWj4.tsx","timestamp":1683371593767}]}